edapy/__init__.py
edapy/__main__.py
edapy/_version.py
edapy/cli.py
edapy/pdf.py
edapy/csv/__init__.py
edapy/csv/describe.py
edapy/csv/interactive_type_finder.py
edapy/csv/utils.py
edapy/images/__init__.py
edapy/images/exif.py
edapy-0.4.1.dist-info/LICENSE
edapy-0.4.1.dist-info/METADATA
edapy-0.4.1.dist-info/WHEEL
edapy-0.4.1.dist-info/entry_points.txt
edapy-0.4.1.dist-info/top_level.txt
edapy-0.4.1.dist-info/RECORD
