Metadata-Version: 2.1
Name: edapy
Version: 0.4.1
Summary: A tookit for exploratoriy data analysis.
Home-page: https://github.com/MartinThoma/edapy
Author: Martin Thoma
Author-email: info@martin-thoma.de
Maintainer: Martin Thoma
Maintainer-email: info@martin-thoma.de
License: MIT
Download-URL: https://github.com/MartinThoma/edapy
Keywords: EDA,Data Science
Platform: Linux
Classifier: Development Status :: 3 - Alpha
Classifier: Environment :: Console
Classifier: Intended Audience :: Developers
Classifier: Intended Audience :: Science/Research
Classifier: Intended Audience :: Information Technology
Classifier: License :: OSI Approved :: MIT License
Classifier: Natural Language :: English
Classifier: Programming Language :: Python :: 3 :: Only
Classifier: Programming Language :: Python :: 3.7
Classifier: Programming Language :: Python :: 3.8
Classifier: Programming Language :: Python :: 3.9
Classifier: Topic :: Scientific/Engineering :: Information Analysis
Classifier: Topic :: Software Development
Classifier: Topic :: Utilities
Requires-Python: >=3.7
Requires-Dist: cfg-load (>=0.3.1)
Requires-Dist: click (>=6.7)
Requires-Dist: pandas (>=0.20.3)
Requires-Dist: Pillow (>=4.2.1)
Requires-Dist: PyPDF2 (>=1.26.0)
Requires-Dist: PyYAML (>=3.12)
Provides-Extra: all
Requires-Dist: pytest ; extra == 'all'
Requires-Dist: pytest-black ; extra == 'all'
Requires-Dist: coverage (<5.0.0) ; extra == 'all'
Requires-Dist: pytest-cov ; extra == 'all'
Requires-Dist: pytest-flake8 ; extra == 'all'
Requires-Dist: pytest-mccabe ; extra == 'all'
Requires-Dist: simplejson ; extra == 'all'
Provides-Extra: tests
Requires-Dist: pytest ; extra == 'tests'
Requires-Dist: pytest-black ; extra == 'tests'
Requires-Dist: coverage (<5.0.0) ; extra == 'tests'
Requires-Dist: pytest-cov ; extra == 'tests'
Requires-Dist: pytest-flake8 ; extra == 'tests'
Requires-Dist: pytest-mccabe ; extra == 'tests'
Requires-Dist: simplejson ; extra == 'tests'
